MANIFEST.in
README.txt
setup.cfg
setup.py
adi/__init__.py
adi.revertorder.egg-info/PKG-INFO
adi.revertorder.egg-info/SOURCES.txt
adi.revertorder.egg-info/dependency_links.txt
adi.revertorder.egg-info/entry_points.txt
adi.revertorder.egg-info/namespace_packages.txt
adi.revertorder.egg-info/not-zip-safe
adi.revertorder.egg-info/paster_plugins.txt
adi.revertorder.egg-info/requires.txt
adi.revertorder.egg-info/top_level.txt
adi/revertorder/__init__.py
adi/revertorder/configure.zcml
adi/revertorder/subscriber.py
adi/revertorder/tests.py
adi/revertorder/profiles/default/metadata.xml
docs/HISTORY.txt
docs/INSTALL.txt
docs/LICENSE.GPL
docs/LICENSE.txt