Metadata-Version: 1.1
Name: adi.revertorder
Version: 1.3
Summary: A Plone addon, to prepend any newly created content-item to its siblings, instead of appending it.
Home-page: https://github.com/ida/adi.revertorder/
Author: Ida Ebkes
Author-email: contact@ida-ebkes.eu
License: GPL
Platform: UNKNOWN
Classifier: Framework :: Plone
Classifier: Programming Language :: Python
